mbs/__init__.py
mbs/corrections.py
mbs/io.py
mbs/krx.py
mbs/resolution.py
mbs/spectra.py
mbs/utils.py
mbs/widgets.py
mbs-0.2.2.dist-info/licenses/LICENSE
mbs-0.2.2.dist-info/METADATA
mbs-0.2.2.dist-info/WHEEL
mbs-0.2.2.dist-info/top_level.txt
mbs-0.2.2.dist-info/RECORD
