Metadata-Version: 2.4
Name: mbs
Version: 0.2.2
Summary: Utilities for MB Scientific analyzer data
Author-email: Johannes Falke <Johannes.Falke@cpfs.mpg.de>
License: GPLv3
Project-URL: homepage, https://github.com/mueslo/mbs
Project-URL: documentation, https://mbsutils.readthedocs.io/
Keywords: arpes,spectroscopy,physics,science
Requires-Python: <4,>=3.9
License-File: LICENSE
Requires-Dist: numpy
Requires-Dist: scipy
Requires-Dist: matplotlib~=3.4
Requires-Dist: pandas
Provides-Extra: docs
Requires-Dist: sphinx~=7.0; extra == "docs"
Requires-Dist: sphinx-rtd-theme; extra == "docs"
Requires-Dist: sphinx-gallery~=0.13; extra == "docs"
Requires-Dist: Pillow; extra == "docs"
Provides-Extra: tests
Requires-Dist: pytest; extra == "tests"
Provides-Extra: xarray
Requires-Dist: xarray; extra == "xarray"
Provides-Extra: widgets
Requires-Dist: jupyterlab<5,>=3.2; extra == "widgets"
Requires-Dist: ipympl~=0.8; extra == "widgets"
Requires-Dist: ipywidgets<9,>=7.6; extra == "widgets"
Dynamic: license-file
